MANIFEST.in
README.md
VERSION
setup.py
fabric_deploy/__init__.py
fabric_deploy/deploy.py
fabric_deploy/options.py
fabric_deploy/scm.py
fabric_deploy/strategy.py
fabric_deploy.egg-info/PKG-INFO
fabric_deploy.egg-info/SOURCES.txt
fabric_deploy.egg-info/dependency_links.txt
fabric_deploy.egg-info/requires.txt
fabric_deploy.egg-info/top_level.txt