Metadata-Version: 1.0
Name: fabric_deploy
Version: 0.4.4
Summary: capistrano like deploy recipe for fabric
Home-page: https://github.com/yyuu/fabric_deploy
Author: Yamashita Yuu
Author-email: yamashita@geishatokyo.com
License: UNKNOWN
Platform: UNKNOWN
